setup.py
phoenix_ml9/Framework.py
phoenix_ml9/__init__.py
phoenix_ml9.egg-info/PKG-INFO
phoenix_ml9.egg-info/SOURCES.txt
phoenix_ml9.egg-info/dependency_links.txt
phoenix_ml9.egg-info/not-zip-safe
phoenix_ml9.egg-info/top_level.txt